nillion_client_proto/__init__.py
nillion_client_proto/nillion/__init__.py
nillion_client_proto/nillion/auth/__init__.py
nillion_client_proto/nillion/auth/v1/__init__.py
nillion_client_proto/nillion/auth/v1/public_key/__init__.py
nillion_client_proto/nillion/auth/v1/token/__init__.py
nillion_client_proto/nillion/auth/v1/user/__init__.py
nillion_client_proto/nillion/compute/__init__.py
nillion_client_proto/nillion/compute/v1/__init__.py
nillion_client_proto/nillion/compute/v1/invoke/__init__.py
nillion_client_proto/nillion/compute/v1/retrieve/__init__.py
nillion_client_proto/nillion/compute/v1/stream/__init__.py
nillion_client_proto/nillion/leader_queries/__init__.py
nillion_client_proto/nillion/leader_queries/v1/__init__.py
nillion_client_proto/nillion/leader_queries/v1/pool_status/__init__.py
nillion_client_proto/nillion/membership/__init__.py
nillion_client_proto/nillion/membership/v1/__init__.py
nillion_client_proto/nillion/membership/v1/cluster/__init__.py
nillion_client_proto/nillion/membership/v1/version/__init__.py
nillion_client_proto/nillion/meta/__init__.py
nillion_client_proto/nillion/meta/v1/__init__.py
nillion_client_proto/nillion/meta/v1/tx_pb2.py
nillion_client_proto/nillion/meta/v1/tx_pb2.pyi
nillion_client_proto/nillion/payments/__init__.py
nillion_client_proto/nillion/payments/v1/__init__.py
nillion_client_proto/nillion/payments/v1/balance/__init__.py
nillion_client_proto/nillion/payments/v1/config/__init__.py
nillion_client_proto/nillion/payments/v1/quote/__init__.py
nillion_client_proto/nillion/payments/v1/receipt/__init__.py
nillion_client_proto/nillion/permissions/__init__.py
nillion_client_proto/nillion/permissions/v1/__init__.py
nillion_client_proto/nillion/permissions/v1/overwrite/__init__.py
nillion_client_proto/nillion/permissions/v1/permissions/__init__.py
nillion_client_proto/nillion/permissions/v1/retrieve/__init__.py
nillion_client_proto/nillion/permissions/v1/update/__init__.py
nillion_client_proto/nillion/preprocessing/__init__.py
nillion_client_proto-0.2.0.dist-info/METADATA
nillion_client_proto-0.2.0.dist-info/WHEEL
nillion_client_proto-0.2.0.dist-info/top_level.txt
nillion_client_proto-0.2.0.dist-info/RECORD
