Metadata-Version: 2.2
Name: nillion-client-proto
Version: 0.2.0
Summary: Nillion client Protobuf files
License: MIT
Classifier: Programming Language :: Python :: 3
Classifier: License :: OSI Approved :: MIT License
Classifier: Operating System :: OS Independent
Requires-Dist: betterproto==2.0.0b7
Requires-Dist: googleapis-common-protos==1.66.0
Provides-Extra: dev
Requires-Dist: grpcio-tools==1.62.3; extra == "dev"
Requires-Dist: betterproto[compiler]==2.0.0b7; extra == "dev"
